Country/ContinentOfCountries.py
Country/CountryCode.py
Country/CountryInfo.py
Country/CountryLanguange.py
Country/MoneyConversion.py
Country/TimeZone.py
Country/__init__.py
Modul/Modul1.py
Modul/Modul2.py
Modul/Modul3.py
Modul/Modul4.py
Modul/Modul5.py
Modul/Modul6.py
Modul/__init__.py
Country_Converter_Toolkit-0.1.1.dist-info/METADATA
Country_Converter_Toolkit-0.1.1.dist-info/WHEEL
Country_Converter_Toolkit-0.1.1.dist-info/top_level.txt
Country_Converter_Toolkit-0.1.1.dist-info/RECORD
