Metadata-Version: 2.1
Name: Country_Converter_Toolkit
Version: 0.1.1
Summary: Package to find out various information about countries: Country Code, Country Language, City and Country Currency Information, Time Conversion, Currency Conversion, and search for Continents from Country Names
Home-page: https://github.com/A-M-Haadi/Country_Converter_Toolkit.git
Author: Kelompok 5 AP B
Author-email: aal3it@gmail.com
Requires-Python: >=3.6
